MANIFEST.in
README.md
setup.py
slack/__init__.py
slack.egg-info/PKG-INFO
slack.egg-info/SOURCES.txt
slack.egg-info/dependency_links.txt
slack.egg-info/top_level.txt