Metadata-Version: 1.1
Name: slack
Version: 0.0.1
Summary: a DI container
Home-page: https://github.com/zweifisch/slack
Author: Feng Zhou
Author-email: zf.pascal@gmail.com
License: MIT
Keywords: DI Container
Platform: UNKNOWN
Classifier: Development Status :: 2 - Pre-Alpha
Classifier: Operating System :: OS Independent
Classifier: Intended Audience :: Developers
Classifier: License :: OSI Approved :: MIT License
Classifier: Programming Language :: Python :: 3.4
